biblioteca_planilhas/__init__.py
biblioteca_planilhas/planilhas.py
biblioteca_planilhas-0.2.dist-info/METADATA
biblioteca_planilhas-0.2.dist-info/WHEEL
biblioteca_planilhas-0.2.dist-info/top_level.txt
biblioteca_planilhas-0.2.dist-info/RECORD
